{
	"tours":[
		{
		  "Name":"Euro Tour",
		  "ArtistName":"Tom & Jerry",
		  "Id":1,
		  "DateStart":"2018-01-01T00:00:00",
		  "DateEnd":"2019-01-01T00:00:00",
		  "Host":"Fred Quimby",
		  "Trips":[
			{            
				"Travellers":[1, 3, 4],
				"Company":"Europe Airlines",            
				"Date":"2018-01-02T00:00:00",
				"TimeDepart":"14:00:00"            
			 },
			 {            
				"Travellers":[ 3, 4],
				"Company":"European Airways",            
				"Date":"2018-02-06T00:00:00",
				"TimeDepart":"14:20:00"            
			 },
			 {            
				"Travellers":[ 1, 2, 3, 4, 5],
				"Company":"European Fast Rail Trains",            
				"Date":"2018-08-028T00:00:00",
				"TimeDepart":"10:10:00"            
			 },
			 {            
				"Travellers":[ 1, 2, 3, 4, 5],
				"Company":"McTrainy McTrainFace",            
				"Date":"2018-08-05T00:00:00",
				"TimeDepart":"09:25:00"        
			 },
			 {            
				"Travellers":[ 1, 2, 3, 4, 5],
				"Company":"McBoaty McBoatFace",            
				"Date":"2018-12-31T00:00:00",
				"TimeDepart":"19:45:00"            
			 }
		  ],
		  "Travellers":[
			{ "Id": 1, "Name": "Adam Smith" },
			{ "Id": 2, "Name": "Jon Doe" },
			{ "Id": 3, "Name": "Kris Bon" },
			{ "Id": 4, "Name": "Jorge Sanchez" },
			{ "Id": 5, "Name": "Raja Lanka" }
		  ],
		  "Contact":{
			 "Name":"Emergency",
			 "Email":"emergency@nosuchwebsite.uk.co",
			 "Phone":"123123123123"
		  }
	   },
	   {
		  "Name":"Asia Tour",
		  "ArtistName":"Geronimo",
		  "Id":2,
		  "DateStart":"2019-01-06T00:00:00",
		  "DateEnd":"2019-01-20T00:00:00",
		  "Host":"Linek Garry",
		  "Trips":[
			{            
				"Travellers":[2, 3, 4],
				"Company":"Asia Airplanes",            
				"Date":"2019-01-06T00:00:00",
				"TimeDepart":"09:00:00"           
			 },
			 {            
				"Travellers":[ 3, 5],
				"Company":"Fast Asian Trains Going Really Fast",            
				"Date":"2019-01-07T00:00:00",
				"TimeDepart":"14:00:00"           
			 },
			 {            
				"Travellers":[ 1, 2, 3, 4, 5],
				"Company":"Catch me if you can",            
				"Date":"2019-01-10T00:00:00",
				"TimeDepart":"17:00:00"            
			 },
			 {            
				"Travellers":[ 1, 5],
				"Company":"Catch me if you can",            
				"Date":"2019-01-12T00:00:00",
				"TimeDepart":"08:30:00"            
			 },
			 {            
				"Travellers":[ 1, 2, 3, 4, 5],
				"Company":"Asia Airplanes",            
				"Date":"2019-01-14T00:00:00",
				"TimeDepart":"21:00:00"            
			 },
			 {            
				"Travellers":[ 1, 2, 3, 4, 5],
				"Company":"Asia Airplanes",            
				"Date":"2019-01-16T00:00:00",
				"TimeDepart":"18:00:00"           
			 },
			 {            
				"Travellers":[ 1, 2, 3, 4, 5],
				"Company":"Fast Asian Trains Going Really Fast",            
				"Date":"2019-01-19T00:00:00",
				"TimeDepart":"19:00:00"            
			 }
		  ],
		  "Travellers":[
			{ "Id": 1, "Name": "Cecilia Jones" },
			{ "Id": 2, "Name": "Jon Doe" },
			{ "Id": 3, "Name": "Kris Bon" },
			{ "Id": 4, "Name": "Jorge Sanchez" },
			{ "Id": 5, "Name": "Xie Hui" }
		  ],
		  "Contact":{
			 "Name":"Emergency",
			 "Email":"emergency@nosuchwebsite.uk.co",
			 "Phone":"123123123123"
		  }
	   },
	   {
		  "Name":"McToury McTourFace",
		  "ArtistName":"McArtist McArtFace",
		  "Id":3,
		  "DateStart":"2018-08-01T00:00:00",
		  "DateEnd":"2018-08-15T00:00:00",
		  "Host":"McHosty McHostFace",
		  "Trips":[
			{            
				"Travellers":[1, 3, 4],
				"Company":"Virgin Atlantic",            
				"Date":"2018-08-02T00:00:00",
				"TimeDepart":"13:00:00"            
			 },
			 {            
				"Travellers":[ 3, 4],
				"Company":"Virgin Atlantic",            
				"Date":"2018-08-05T00:00:00",
				"TimeDepart":"12:00:00"            
			 },
			 {            
				"Travellers":[ 1, 2, 3, 4, 5],
				"Company":"Virgin Atlantic",            
				"Date":"2018-08-06T00:00:00",
				"TimeDepart":"11:00:00"            
			 },
			 {            
				"Travellers":[ 1, 2, 3, 4, 5],
				"Company":"Virgin Atlantic",            
				"Date":"2018-08-10T00:00:00",
				"TimeDepart":"10:00:00"            
			 },
			 {            
				"Travellers":[ 1, 2, 3, 4, 5],
				"Company":"Virgin Atlantic",            
				"Date":"2018-08-14T00:00:00",
				"TimeDepart":"09:00:00"            
			 }
		  ],
		  "Travellers":[
			{ "Id": 1, "Name": "Lisa" },
			{ "Id": 2, "Name": "Jon Doe" },
			{ "Id": 3, "Name": "Kris Bon" },
			{ "Id": 4, "Name": "Jorge Sanchez" },
			{ "Id": 5, "Name": "Winnie" }
		  ],
		  "Contact":{
			 "Name":"Emergency",
			 "Email":"emergency@nosuchwebsite.uk.co",
			 "Phone":"123123123123"
		  }
	   }
	]
}